dadjokes/__init__.py
dadjokes/constants.py
dadjokes/dadjokes.py
dadjokes-1.3.2.data/scripts/dadjokes
dadjokes-1.3.2.dist-info/LICENSE
dadjokes-1.3.2.dist-info/METADATA
dadjokes-1.3.2.dist-info/WHEEL
dadjokes-1.3.2.dist-info/top_level.txt
dadjokes-1.3.2.dist-info/RECORD
