Metadata-Version: 2.1
Name: dadjokes
Version: 1.3.2
Summary: icanhazdadjoke api wrapper
Home-page: https://github.com/crossnox/dadjokes
Author: CrossNox
License: UNKNOWN
Platform: UNKNOWN
Classifier: Programming Language :: Python :: 3
Provides-Extra: dev
